MANIFEST.in
setup.py
conformine/README.md
conformine/__init__.py
conformine.egg-info/PKG-INFO
conformine.egg-info/SOURCES.txt
conformine.egg-info/dependency_links.txt
conformine.egg-info/requires.txt
conformine.egg-info/top_level.txt
conformine/utils/__init__.py
conformine/utils/data_utils.py
conformine/utils/dataset_utils.py
conformine/utils/from_fasta_standalone_predictor.py
conformine/utils/network_utils.py
conformine/utils/pytorch_models.py
conformine/utils/models/113_correct_normalization_parameters.json
conformine/utils/models/__init__.py
conformine/utils/models/minmax_scaler_bw_0.13_ground_clean_1.2.1.pkl
conformine/utils/models/minmax_scaler_bw_0.13_ground_clean_1.22.4.pkl
conformine/utils/models/minmax_scaler_bw_0.13_ground_clean_pickle_version_1.2.1.pkl
conformine/utils/models/minmax_scaler_bw_0.13_ground_sklearn_1.2.1.pkl
conformine/utils/models/minmax_scaler_ground_sklearn_1.2.1.pkl
conformine/utils/models/normalization_parameters.json
conformine/utils/models/state_dictionary_torch_model.pt
conformine/utils/models/state_dictionary_torch_model_bw_0.13.pt
conformine/utils/models/state_dictionary_torch_model_bw_0.13_clean.pt
conformine/wrapper_source/__init__.py
conformine/wrapper_source/conformine_wrapper.py