Metadata-Version: 2.1
Name: conformine
Version: 0.0.1b12
Summary: ConforMine, a predictor of conformational variability from amino acid sequence
Author: Jose Gavalda-Garcia
Author-email: jose.gavalda.garcia@vub.be
Maintainer: Jose Gavalda-Garcia, Adrian Diaz, Wim Vranken
Maintainer-email: jose.gavalda.garcia@vub.be, adrian.diaz@vub.be, wim.vranken@vub.be
Keywords: b2bTools,biology,bioinformatics,bio-informatics,fasta,proteins,protein-conformation,conformational-variability
Classifier: Natural Language :: English
Classifier: Programming Language :: Python :: 3.7
Classifier: Programming Language :: Python :: 3.8
Classifier: Programming Language :: Python :: 3.9
Classifier: License :: OSI Approved :: GNU General Public License v3 (GPLv3)
Classifier: Operating System :: MacOS
Classifier: Operating System :: POSIX :: Linux
Classifier: Topic :: Scientific/Engineering :: Bio-Informatics
Classifier: Topic :: Scientific/Engineering :: Chemistry
Classifier: Topic :: Scientific/Engineering :: Physics
Classifier: Intended Audience :: Science/Research
Classifier: Intended Audience :: Education
Requires-Python: >=3.6, <3.10
